moldclone/__init__.py
moldclone/moldclone.py
moldclone-2.0.0.dist-info/LICENSE
moldclone-2.0.0.dist-info/METADATA
moldclone-2.0.0.dist-info/WHEEL
moldclone-2.0.0.dist-info/entry_points.txt
moldclone-2.0.0.dist-info/top_level.txt
moldclone-2.0.0.dist-info/RECORD
