Metadata-Version: 2.1
Name: moldclone
Version: 2.0.0
Summary: FACEBOOK ACCOUNT CLONER
Home-page: https://gitHub.com/Moajjem404
Author: MOAJJEM
Author-email: adethkhan@gmail.com
License: MIT
Keywords: hacker,tool,prank,termux,hack,FB CLONE,CLONER,MOAJJEM,hack fb,facebook,cloning,python,python cloning,python2,python facebook crack,facebook,new cloner,facebook hack
Platform: UNKNOWN
Classifier: Development Status :: 4 - Beta
Classifier: Intended Audience :: Developers
Classifier: Topic :: Software Development :: Libraries :: Python Modules
Classifier: License :: OSI Approved :: MIT License
Classifier: Programming Language :: Python :: 2
Classifier: Operating System :: OS Independent
Classifier: Environment :: Console
Requires-Python: <=2.7.18
Requires-Dist: mechanize
Requires-Dist: requests
